aaronparse/__init__.py
aaronparse/easymode.py
aaronparse/execution.py
aaronparse/parser.py
aaronparse/process_namespace.py
aaronparse-0.3.2.dist-info/LICENSE.txt
aaronparse-0.3.2.dist-info/METADATA
aaronparse-0.3.2.dist-info/WHEEL
aaronparse-0.3.2.dist-info/top_level.txt
aaronparse-0.3.2.dist-info/RECORD
