Metadata-Version: 2.1
Name: aaronparse
Version: 0.3.2
Summary: easy cooperation between main-function and argparse
Author-email: Aaron Alphabet <aaron.alphabet@posteo.org>
License: Copyright © 2023 Aaron Alphabet
Project-URL: source, https://github.com/aaron-alphabet/aaronparse
Classifier: License :: OSI Approved :: MIT License
Classifier: Programming Language :: Python
Classifier: Programming Language :: Python :: 3
Requires-Python: >=3.11
License-File: LICENSE.txt
Requires-Dist: funcinputs >=0.0.5
